hmytb/__init__.py
hmytb/animals.py
hmytb/config.py
hmytb/harmony_client.py
hmytb/harmony_commands.py
hmytb/harmony_notifications.py
hmytb/harmony_wallets.py
hmytb-1.0.5.dist-info/METADATA
hmytb-1.0.5.dist-info/WHEEL
hmytb-1.0.5.dist-info/top_level.txt
hmytb-1.0.5.dist-info/RECORD
