Metadata-Version: 2.1
Name: hmytb
Version: 1.0.5
Summary: Harmony ONE command line wallet tools
Home-page: https://github.com/easy-node-pro/hmytb
Author: EasyNode.PRO
Author-email: support@easynode.pro
Project-URL: Bug Tracker, https://github.com/easy-node-pro/hmytb/issues
Project-URL: repository, https://github.com/easy-node-pro/hmytb
Classifier: Programming Language :: Python :: 3
Classifier: License :: OSI Approved :: MIT License
Classifier: Operating System :: OS Independent
Requires-Python: >=3.9
Requires-Dist: aiohttp
Requires-Dist: asyncio
Requires-Dist: argparse
Requires-Dist: python-dotenv
Requires-Dist: requests
Provides-Extra: dev
Requires-Dist: aiohttp; extra == "dev"
Requires-Dist: asyncio; extra == "dev"
Requires-Dist: argparse; extra == "dev"
Requires-Dist: python-dotenv; extra == "dev"
Requires-Dist: requests; extra == "dev"
Requires-Dist: wheel; extra == "dev"
Requires-Dist: build; extra == "dev"
Requires-Dist: twine; extra == "dev"
